wcps/__init__.py
wcps/model.py
wcps/service.py
wcps/spectral.py
wcps-0.5.4.dist-info/licenses/LICENSE
wcps-0.5.4.dist-info/METADATA
wcps-0.5.4.dist-info/WHEEL
wcps-0.5.4.dist-info/top_level.txt
wcps-0.5.4.dist-info/RECORD
