Metadata-Version: 2.4
Name: wcps
Version: 0.5.4
Summary: Python client library for WCPS (OGC Web Coverage Processing Service) backends.
Author-email: Dimitar Misev <misev@rasdaman.com>
Project-URL: Documentation, https://rasdaman.github.io/wcps-python-client/
Project-URL: Source, https://github.com/rasdaman/wcps-python-client
Project-URL: Issues, https://github.com/rasdaman/wcps-python-client/issues
Keywords: wcps,rasdaman,ogc,gis,Web Coverage Processing Service
Classifier: Programming Language :: Python :: 3
Classifier: Programming Language :: Python :: 3.10
Classifier: Programming Language :: Python :: 3.11
Classifier: Programming Language :: Python :: 3.12
Classifier: License :: OSI Approved :: GNU Lesser General Public License v3 (LGPLv3)
Classifier: Operating System :: OS Independent
Classifier: Development Status :: 2 - Pre-Alpha
Classifier: Topic :: Database :: Front-Ends
Classifier: Topic :: Scientific/Engineering :: GIS
Classifier: Topic :: Software Development :: Libraries
Requires-Python: >=3.10
License-File: LICENSE
Requires-Dist: requests
Provides-Extra: docs
Requires-Dist: sphinx-autoapi; extra == "docs"
Requires-Dist: sphinx; extra == "docs"
Requires-Dist: recommonmark; extra == "docs"
Provides-Extra: tests
Requires-Dist: pytest; extra == "tests"
Requires-Dist: numpy; extra == "tests"
Requires-Dist: Pillow; extra == "tests"
Requires-Dist: netCDF4; extra == "tests"
Dynamic: license-file
